threading_manager/__init__.py
threading_manager/main.py
threading_manager-0.0.8.dist-info/LICENSE
threading_manager-0.0.8.dist-info/METADATA
threading_manager-0.0.8.dist-info/WHEEL
threading_manager-0.0.8.dist-info/top_level.txt
threading_manager-0.0.8.dist-info/RECORD
